maykin_2fa/__init__.py
maykin_2fa/admin.py
maykin_2fa/apps.py
maykin_2fa/checks.py
maykin_2fa/decorators.py
maykin_2fa/hijack.py
maykin_2fa/hijack_signals.py
maykin_2fa/middleware.py
maykin_2fa/py.typed
maykin_2fa/signals.py
maykin_2fa/typing.py
maykin_2fa/urls.py
maykin_2fa/views.py
maykin_2fa/locale/nl/LC_MESSAGES/django.mo
maykin_2fa/locale/nl/LC_MESSAGES/django.po
maykin_2fa/static/maykin_2fa/css/fixes.css
maykin_2fa/templates/maykin_2fa/account_security.html
maykin_2fa/templates/maykin_2fa/backup_tokens.html
maykin_2fa/templates/maykin_2fa/base.html
maykin_2fa/templates/maykin_2fa/login.html
maykin_2fa/templates/maykin_2fa/recovery_token.html
maykin_2fa/templates/maykin_2fa/setup.html
maykin_2fa/templates/maykin_2fa/setup_complete.html
maykin_2fa/templates/maykin_2fa/includes/wizard_actions.html
maykin_2fa/templates/maykin_2fa/includes/wizard_form.html
maykin_2fa/test/__init__.py
maykin_2fa-2.0.1.dist-info/licenses/LICENSE
maykin_2fa-2.0.1.dist-info/METADATA
maykin_2fa-2.0.1.dist-info/WHEEL
maykin_2fa-2.0.1.dist-info/top_level.txt
maykin_2fa-2.0.1.dist-info/RECORD
