Metadata-Version: 2.4
Name: maykin-2fa
Version: 2.0.1
Summary: An opinionated integration of django-two-factor-auth in the Django admin interface.
Author-email: Maykin Media <support@maykinmedia.nl>
License-Expression: MIT
Project-URL: Homepage, https://github.com/maykinmedia/maykin-2fa
Project-URL: Documentation, http://maykin-2fa.readthedocs.io/en/latest/
Project-URL: Bug Tracker, https://github.com/maykinmedia/maykin-2fa/issues
Project-URL: Source Code, https://github.com/maykinmedia/maykin-2fa
Project-URL: Changelog, https://github.com/maykinmedia/maykin-2fa/blob/main/CHANGELOG.rst
Keywords: django,two factor,2fa,mfa,multi factor auth
Classifier: Development Status :: 5 - Production/Stable
Classifier: Framework :: Django
Classifier: Framework :: Django :: 4.2
Classifier: Framework :: Django :: 5.2
Classifier: Framework :: Django :: 6.0
Classifier: Intended Audience :: Developers
Classifier: Operating System :: Unix
Classifier: Operating System :: MacOS
Classifier: Operating System :: Microsoft :: Windows
Classifier: Programming Language :: Python :: 3.12
Classifier: Programming Language :: Python :: 3.13
Classifier: Programming Language :: Python :: 3.14
Classifier: Topic :: Software Development :: Libraries :: Python Modules
Requires-Python: >=3.12
License-File: LICENSE
Requires-Dist: django>=4.2
Requires-Dist: django-two-factor-auth[webauthn]>=1.18.1
Requires-Dist: django-otp>=1.7.0
Provides-Extra: tests
Requires-Dist: pytest; extra == "tests"
Requires-Dist: pytest-django; extra == "tests"
Requires-Dist: pytest-cov; extra == "tests"
Requires-Dist: tox; extra == "tests"
Requires-Dist: ruff; extra == "tests"
Provides-Extra: docs
Requires-Dist: sphinx; extra == "docs"
Requires-Dist: sphinx-rtd-theme; extra == "docs"
Provides-Extra: release
Requires-Dist: bump-my-version; extra == "release"
Dynamic: license-file
